ejemplos/test/source/map9v3.v
/* 
 *--------------------------------------------------------------
 * This module converts a counter value N into a reset value
 * for an 8-bit LFSR.  The count is initialized by "reset" high
 * or "start" transition high.  When the count is valid, it is
 * latched into "dp" and the signal "done" is raised to indicate
 * a valid new value of "dp".
 *--------------------------------------------------------------
 */

module map9v3(clock, reset, start, N, dp, done, counter, sr);

input         clock;
input	      start;         // run at rising edge of start
input	      reset;         // high is reset case ( run after reset)
input   [8:0] N;             // the number to divide by

output  [8:0] dp;	     // these outputs drive an LFSR counter
output	      done;
output	[7:0] counter;
output  [7:0] sr;

reg     [8:0] dp;	   
reg	[7:0] sr;
reg	[7:0] counter;
reg	      startbuf;
reg	      done;
reg	[2:0] state;

parameter INIT 		= 3'b000;
parameter RUN 		= 3'b001;
parameter ALMOSTDONE 	= 3'b010;
parameter DONE 		= 3'b011;
parameter WAIT 		= 3'b100;


always @(posedge clock or posedge reset) begin

    if (reset == 1) begin

	dp <= 9'b0;
	sr <= 8'b0;
	counter <= 8'b0;
	startbuf <= 0;
	done <= 0;
	state <= INIT;

    end else begin

	if (state == INIT) begin
	    counter <= 255 - N[8:1] + 3;
	    sr <= 8'b0;
	    done <= 0;
	    state <= RUN;

	end else if (state == RUN) begin
	    sr[7] <= sr[6];
	    sr[6] <= sr[5];
	    sr[5] <= sr[4];
	    sr[4] <= sr[3];
	    sr[3] <= sr[2];
	    sr[2] <= sr[1];
	    sr[1] <= sr[0];
	    sr[0] <= ~(sr[7] ^ sr[5] ^ sr[4] ^ sr[3]);
	    counter <= counter - 1;
	    if (counter == 0) begin
	       state <= ALMOSTDONE;
	    end

	end else if (state == ALMOSTDONE) begin
	    dp[0] <= N[0];
	    dp[8:1] <= sr[7:0];
	    state <= DONE;

	end else if (state == DONE) begin
	    done <= 1;
	    state <= WAIT;

	end else if (state == WAIT) begin
	    if (start == 1 && startbuf == 0) begin
		state <= INIT;
	    end
	end

	startbuf <= start;
    end
end

endmodule

ejemplos/test/rtl/map9v3_tb.v
module map9v3_tb;

  /* Make a reset that pulses once. */
  reg start = 0;
  reg reset = 1;
  reg [8:0] N = 220;
  initial begin
     $dumpfile("map9v3_tb.vcd");
     $dumpvars(0,map9v3_tb);

     # 500   reset = 0;
     # 500   start = 1;
     # 500   start = 0;
     # 40000 start = 1;
     # 500   start = 0;
     # 50000 $stop;
  end

  /* Make a regular pulsing clock. */
  reg clock = 0;
  always #100 clock = !clock;


  wire [8:0] dp;
  wire [7:0] sr;
  wire [7:0] counter;
  wire done;
  map9v3 map9v3_inst(clock, reset, start, N, dp, done, counter, sr);

  initial
     $monitor("At time %t, counter = %h (%0d)",
              $time, counter , counter);
endmodule // map9v3_tb

ejemplos/test/rtl/map9v3_tb.vcd
$date
	Thu Apr 16 23:40:03 2015
$end
$version
	Icarus Verilog
$end
$timescale
	1s
$end
$scope module map9v3_tb $end
$var wire 8 ! sr [7:0] $end
$var wire 9 " dp [8:0] $end
$var wire 1 # done $end
$var wire 8 $ counter [7:0] $end
$var reg 9 % N [8:0] $end
$var reg 1 & clock $end
$var reg 1 ' reset $end
$var reg 1 ( start $end
$scope module map9v3_inst $end
$var wire 9 ) N [8:0] $end
$var wire 1 & clock $end
$var wire 1 ' reset $end
$var wire 1 ( start $end
$var reg 8 * counter [7:0] $end
$var reg 1 # done $end
$var reg 9 + dp [8:0] $end
$var reg 8 , sr [7:0] $end
$var reg 1 - startbuf $end
$var reg 3 . state [2:0] $end
$upscope $end
$upscope $end
$enddefinitions $end
#0
$dumpvars
b0 .
0-
b0 ,
b0 +
b0 *
b11011100 )
0(
1'
0&
b11011100 %
b0 $
0#
b0 "
b0 !
$end
#100
1&
#200
0&
#300
1&
#400
0&
#500
b1 .
b10010100 $
b10010100 *
1&
0'
#600
0&
#700
b10010011 $
b10010011 *
b1 !
b1 ,
1&
#800
0&
#900
b10010010 $
b10010010 *
b11 !
b11 ,
1&
#1000
0&
1(
#1100
1-
b10010001 $
b10010001 *
b111 !
b111 ,
1&
#1200
0&
#1300
b10010000 $
b10010000 *
b1111 !
b1111 ,
1&
#1400
0&
#1500
0-
b10001111 $
b10001111 *
b11110 !
b11110 ,
1&
0(
#1600
0&
#1700
b10001110 $
b10001110 *
b111101 !
b111101 ,
1&
#1800
0&
#1900
b10001101 $
b10001101 *
b1111010 !
b1111010 ,
1&
#2000
0&
#2100
b10001100 $
b10001100 *
b11110100 !
b11110100 ,
1&
#2200
0&
#2300
b10001011 $
b10001011 *
b11101000 !
b11101000 ,
1&
#2400
0&
#2500
b10001010 $
b10001010 *
b11010000 !
b11010000 ,
1&
#2600
0&
#2700
b10001001 $
b10001001 *
b10100001 !
b10100001 ,
1&
#2800
0&
#2900
b10001000 $
b10001000 *
b1000011 !
b1000011 ,
1&
#3000
0&
#3100
b10000111 $
b10000111 *
b10000111 !
b10000111 ,
1&
#3200
0&
#3300
b10000110 $
b10000110 *
b1110 !
b1110 ,
1&
#3400
0&
#3500
b10000101 $
b10000101 *
b11100 !
b11100 ,
1&
#3600
0&
#3700
b10000100 $
b10000100 *
b111001 !
b111001 ,
1&
#3800
0&
#3900
b10000011 $
b10000011 *
b1110010 !
b1110010 ,
1&
#4000
0&
#4100
b10000010 $
b10000010 *
b11100101 !
b11100101 ,
1&
#4200
0&
#4300
b10000001 $
b10000001 *
b11001011 !
b11001011 ,
1&
#4400
0&
#4500
b10000000 $
b10000000 *
b10010111 !
b10010111 ,
1&
#4600
0&
#4700
b1111111 $
b1111111 *
b101111 !
b101111 ,
1&
#4800
0&
#4900
b1111110 $
b1111110 *
b1011111 !
b1011111 ,
1&
#5000
0&
#5100
b1111101 $
b1111101 *
b10111111 !
b10111111 ,
1&
#5200
0&
#5300
b1111100 $
b1111100 *
b1111111 !
b1111111 ,
1&
#5400
0&
#5500
b1111011 $
b1111011 *
b11111110 !
b11111110 ,
1&
#5600
0&
#5700
b1111010 $
b1111010 *
b11111101 !
b11111101 ,
1&
#5800
0&
#5900
b1111001 $
b1111001 *
b11111011 !
b11111011 ,
1&
#6000
0&
#6100
b1111000 $
b1111000 *
b11110111 !
b11110111 ,
1&
#6200
0&
#6300
b1110111 $
b1110111 *
b11101110 !
b11101110 ,
1&
#6400
0&
#6500
b1110110 $
b1110110 *
b11011100 !
b11011100 ,
1&
#6600
0&
#6700
b1110101 $
b1110101 *
b10111000 !
b10111000 ,
1&
#6800
0&
#6900
b1110100 $
b1110100 *
b1110001 !
b1110001 ,
1&
#7000
0&
#7100
b1110011 $
b1110011 *
b11100011 !
b11100011 ,
1&
#7200
0&
#7300
b1110010 $
b1110010 *
b11000111 !
b11000111 ,
1&
#7400
0&
#7500
b1110001 $
b1110001 *
b10001110 !
b10001110 ,
1&
#7600
0&
#7700
b1110000 $
b1110000 *
b11101 !
b11101 ,
1&
#7800
0&
#7900
b1101111 $
b1101111 *
b111011 !
b111011 ,
1&
#8000
0&
#8100
b1101110 $
b1101110 *
b1110110 !
b1110110 ,
1&
#8200
0&
#8300
b1101101 $
b1101101 *
b11101101 !
b11101101 ,
1&
#8400
0&
#8500
b1101100 $
b1101100 *
b11011010 !
b11011010 ,
1&
#8600
0&
#8700
b1101011 $
b1101011 *
b10110100 !
b10110100 ,
1&
#8800
0&
#8900
b1101010 $
b1101010 *
b1101000 !
b1101000 ,
1&
#9000
0&
#9100
b1101001 $
b1101001 *
b11010001 !
b11010001 ,
1&
#9200
0&
#9300
b1101000 $
b1101000 *
b10100011 !
b10100011 ,
1&
#9400
0&
#9500
b1100111 $
b1100111 *
b1000111 !
b1000111 ,
1&
#9600
0&
#9700
b1100110 $
b1100110 *
b10001111 !
b10001111 ,
1&
#9800
0&
#9900
b1100101 $
b1100101 *
b11111 !
b11111 ,
1&
#10000
0&
#10100
b1100100 $
b1100100 *
b111111 !
b111111 ,
1&
#10200
0&
#10300
b1100011 $
b1100011 *
b1111110 !
b1111110 ,
1&
#10400
0&
#10500
b1100010 $
b1100010 *
b11111100 !
b11111100 ,
1&
#10600
0&
#10700
b1100001 $
b1100001 *
b11111001 !
b11111001 ,
1&
#10800
0&
#10900
b1100000 $
b1100000 *
b11110011 !
b11110011 ,
1&
#11000
0&
#11100
b1011111 $
b1011111 *
b11100110 !
b11100110 ,
1&
#11200
0&
#11300
b1011110 $
b1011110 *
b11001101 !
b11001101 ,
1&
#11400
0&
#11500
b1011101 $
b1011101 *
b10011011 !
b10011011 ,
1&
#11600
0&
#11700
b1011100 $
b1011100 *
b110110 !
b110110 ,
1&
#11800
0&
#11900
b1011011 $
b1011011 *
b1101101 !
b1101101 ,
1&
#12000
0&
#12100
b1011010 $
b1011010 *
b11011011 !
b11011011 ,
1&
#12200
0&
#12300
b1011001 $
b1011001 *
b10110110 !
b10110110 ,
1&
#12400
0&
#12500
b1011000 $
b1011000 *
b1101100 !
b1101100 ,
1&
#12600
0&
#12700
b1010111 $
b1010111 *
b11011001 !
b11011001 ,
1&
#12800
0&
#12900
b1010110 $
b1010110 *
b10110010 !
b10110010 ,
1&
#13000
0&
#13100
b1010101 $
b1010101 *
b1100100 !
b1100100 ,
1&
#13200
0&
#13300
b1010100 $
b1010100 *
b11001000 !
b11001000 ,
1&
#13400
0&
#13500
b1010011 $
b1010011 *
b10010001 !
b10010001 ,
1&
#13600
0&
#13700
b1010010 $
b1010010 *
b100011 !
b100011 ,
1&
#13800
0&
#13900
b1010001 $
b1010001 *
b1000110 !
b1000110 ,
1&
#14000
0&
#14100
b1010000 $
b1010000 *
b10001101 !
b10001101 ,
1&
#14200
0&
#14300
b1001111 $
b1001111 *
b11011 !
b11011 ,
1&
#14400
0&
#14500
b1001110 $
b1001110 *
b110111 !
b110111 ,
1&
#14600
0&
#14700
b1001101 $
b1001101 *
b1101111 !
b1101111 ,
1&
#14800
0&
#14900
b1001100 $
b1001100 *
b11011111 !
b11011111 ,
1&
#15000
0&
#15100
b1001011 $
b1001011 *
b10111110 !
b10111110 ,
1&
#15200
0&
#15300
b1001010 $
b1001010 *
b1111101 !
b1111101 ,
1&
#15400
0&
#15500
b1001001 $
b1001001 *
b11111010 !
b11111010 ,
1&
#15600
0&
#15700
b1001000 $
b1001000 *
b11110101 !
b11110101 ,
1&
#15800
0&
#15900
b1000111 $
b1000111 *
b11101010 !
b11101010 ,
1&
#16000
0&
#16100
b1000110 $
b1000110 *
b11010100 !
b11010100 ,
1&
#16200
0&
#16300
b1000101 $
b1000101 *
b10101001 !
b10101001 ,
1&
#16400
0&
#16500
b1000100 $
b1000100 *
b1010010 !
b1010010 ,
1&
#16600
0&
#16700
b1000011 $
b1000011 *
b10100100 !
b10100100 ,
1&
#16800
0&
#16900
b1000010 $
b1000010 *
b1001001 !
b1001001 ,
1&
#17000
0&
#17100
b1000001 $
b1000001 *
b10010010 !
b10010010 ,
1&
#17200
0&
#17300
b1000000 $
b1000000 *
b100101 !
b100101 ,
1&
#17400
0&
#17500
b111111 $
b111111 *
b1001010 !
b1001010 ,
1&
#17600
0&
#17700
b111110 $
b111110 *
b10010100 !
b10010100 ,
1&
#17800
0&
#17900
b111101 $
b111101 *
b101001 !
b101001 ,
1&
#18000
0&
#18100
b111100 $
b111100 *
b1010011 !
b1010011 ,
1&
#18200
0&
#18300
b111011 $
b111011 *
b10100110 !
b10100110 ,
1&
#18400
0&
#18500
b111010 $
b111010 *
b1001101 !
b1001101 ,
1&
#18600
0&
#18700
b111001 $
b111001 *
b10011010 !
b10011010 ,
1&
#18800
0&
#18900
b111000 $
b111000 *
b110100 !
b110100 ,
1&
#19000
0&
#19100
b110111 $
b110111 *
b1101001 !
b1101001 ,
1&
#19200
0&
#19300
b110110 $
b110110 *
b11010011 !
b11010011 ,
1&
#19400
0&
#19500
b110101 $
b110101 *
b10100111 !
b10100111 ,
1&
#19600
0&
#19700
b110100 $
b110100 *
b1001111 !
b1001111 ,
1&
#19800
0&
#19900
b110011 $
b110011 *
b10011110 !
b10011110 ,
1&
#20000
0&
#20100
b110010 $
b110010 *
b111100 !
b111100 ,
1&
#20200
0&
#20300
b110001 $
b110001 *
b1111000 !
b1111000 ,
1&
#20400
0&
#20500
b110000 $
b110000 *
b11110000 !
b11110000 ,
1&
#20600
0&
#20700
b101111 $
b101111 *
b11100000 !
b11100000 ,
1&
#20800
0&
#20900
b101110 $
b101110 *
b11000001 !
b11000001 ,
1&
#21000
0&
#21100
b101101 $
b101101 *
b10000010 !
b10000010 ,
1&
#21200
0&
#21300
b101100 $
b101100 *
b100 !
b100 ,
1&
#21400
0&
#21500
b101011 $
b101011 *
b1001 !
b1001 ,
1&
#21600
0&
#21700
b101010 $
b101010 *
b10010 !
b10010 ,
1&
#21800
0&
#21900
b101001 $
b101001 *
b100100 !
b100100 ,
1&
#22000
0&
#22100
b101000 $
b101000 *
b1001000 !
b1001000 ,
1&
#22200
0&
#22300
b100111 $
b100111 *
b10010000 !
b10010000 ,
1&
#22400
0&
#22500
b100110 $
b100110 *
b100001 !
b100001 ,
1&
#22600
0&
#22700
b100101 $
b100101 *
b1000010 !
b1000010 ,
1&
#22800
0&
#22900
b100100 $
b100100 *
b10000101 !
b10000101 ,
1&
#23000
0&
#23100
b100011 $
b100011 *
b1010 !
b1010 ,
1&
#23200
0&
#23300
b100010 $
b100010 *
b10100 !
b10100 ,
1&
#23400
0&
#23500
b100001 $
b100001 *
b101000 !
b101000 ,
1&
#23600
0&
#23700
b100000 $
b100000 *
b1010001 !
b1010001 ,
1&
#23800
0&
#23900
b11111 $
b11111 *
b10100010 !
b10100010 ,
1&
#24000
0&
#24100
b11110 $
b11110 *
b1000101 !
b1000101 ,
1&
#24200
0&
#24300
b11101 $
b11101 *
b10001011 !
b10001011 ,
1&
#24400
0&
#24500
b11100 $
b11100 *
b10111 !
b10111 ,
1&
#24600
0&
#24700
b11011 $
b11011 *
b101110 !
b101110 ,
1&
#24800
0&
#24900
b11010 $
b11010 *
b1011101 !
b1011101 ,
1&
#25000
0&
#25100
b11001 $
b11001 *
b10111011 !
b10111011 ,
1&
#25200
0&
#25300
b11000 $
b11000 *
b1110111 !
b1110111 ,
1&
#25400
0&
#25500
b10111 $
b10111 *
b11101111 !
b11101111 ,
1&
#25600
0&
#25700
b10110 $
b10110 *
b11011110 !
b11011110 ,
1&
#25800
0&
#25900
b10101 $
b10101 *
b10111100 !
b10111100 ,
1&
#26000
0&
#26100
b10100 $
b10100 *
b1111001 !
b1111001 ,
1&
#26200
0&
#26300
b10011 $
b10011 *
b11110010 !
b11110010 ,
1&
#26400
0&
#26500
b10010 $
b10010 *
b11100100 !
b11100100 ,
1&
#26600
0&
#26700
b10001 $
b10001 *
b11001001 !
b11001001 ,
1&
#26800
0&
#26900
b10000 $
b10000 *
b10010011 !
b10010011 ,
1&
#27000
0&
#27100
b1111 $
b1111 *
b100111 !
b100111 ,
1&
#27200
0&
#27300
b1110 $
b1110 *
b1001110 !
b1001110 ,
1&
#27400
0&
#27500
b1101 $
b1101 *
b10011100 !
b10011100 ,
1&
#27600
0&
#27700
b1100 $
b1100 *
b111000 !
b111000 ,
1&
#27800
0&
#27900
b1011 $
b1011 *
b1110000 !
b1110000 ,
1&
#28000
0&
#28100
b1010 $
b1010 *
b11100001 !
b11100001 ,
1&
#28200
0&
#28300
b1001 $
b1001 *
b11000011 !
b11000011 ,
1&
#28400
0&
#28500
b1000 $
b1000 *
b10000110 !
b10000110 ,
1&
#28600
0&
#28700
b111 $
b111 *
b1100 !
b1100 ,
1&
#28800
0&
#28900
b110 $
b110 *
b11000 !
b11000 ,
1&
#29000
0&
#29100
b101 $
b101 *
b110001 !
b110001 ,
1&
#29200
0&
#29300
b100 $
b100 *
b1100011 !
b1100011 ,
1&
#29400
0&
#29500
b11 $
b11 *
b11000110 !
b11000110 ,
1&
#29600
0&
#29700
b10 $
b10 *
b10001100 !
b10001100 ,
1&
#29800
0&
#29900
b1 $
b1 *
b11001 !
b11001 ,
1&
#30000
0&
#30100
b0 $
b0 *
b110011 !
b110011 ,
1&
#30200
0&
#30300
b10 .
b11111111 $
b11111111 *
b1100111 !
b1100111 ,
1&
#30400
0&
#30500
b11 .
b11001110 "
b11001110 +
1&
#30600
0&
#30700
b100 .
1#
1&
